ffx/__init__.py
ffx/main.py
ffx/common/__init__.py
ffx/common/loaders.py
ffx/customizations/__init__.py
ffx/customizations/models.py
ffx/data/items/armors.txt
ffx/data/items/template.txt
ffx/data/items/weapons.txt
ffx/data/monsters/monsters.txt
ffx/data/monsters/template.txt
ffx/monsters/__init__.py
ffx/monsters/models.py
ffx_customization_tool-1.0.0.dist-info/METADATA
ffx_customization_tool-1.0.0.dist-info/WHEEL
ffx_customization_tool-1.0.0.dist-info/entry_points.txt
ffx_customization_tool-1.0.0.dist-info/top_level.txt
ffx_customization_tool-1.0.0.dist-info/RECORD
