Metadata-Version: 2.1
Name: ffx-customization-tool
Version: 1.0.0
Summary: FFX Customization Weapon/Armor Tool
Home-page: UNKNOWN
Author: Santiago Blanco Ventas
Author-email: sblancov84@gmail.com
License: MIT
Project-URL: Source, https://gitlab.com/sblancov84/ffx-customization-tool
Platform: UNKNOWN
Requires-Python: >=3.7
Requires-Dist: ttp (==0.4.0)
Requires-Dist: simple-term-menu (==0.10.1)
Requires-Dist: terminaltables (==3.1.0)
